<fest:template xmlns:fest="http://fest.mail.ru" context_name="data">
<div class="ui grid one about_team">
    <div class="ui animated huge list">
        <div class="item">
            <a href="https://github.com/frontend-park-mail-ru/2016_2_Brain404" target="_blank" class="ui">
                <i class="github pink icon"></i>
            </a>
        </div>
        <div class="item">
            <a href="#" class="ui">
                <i class="credit card alternative pink icon"></i>
            </a>
        </div>
    </div>
</div>

    </fest:template>
